jsonltui/__init__.py
jsonltui/main.py
jsonltui/web_template.html
jsonltui-0.1.0.dist-info/LICENSE
jsonltui-0.1.0.dist-info/METADATA
jsonltui-0.1.0.dist-info/WHEEL
jsonltui-0.1.0.dist-info/entry_points.txt
jsonltui-0.1.0.dist-info/top_level.txt
jsonltui-0.1.0.dist-info/RECORD
