Metadata-Version: 2.1
Name: jsonltui
Version: 0.1.0
Summary: A TUI application to visually inspect and navigate JSON and JSONL data
Home-page: https://github.com/gr-b/jsonltui
License: MIT
Platform: UNKNOWN
Classifier: Programming Language :: Python :: 3
Classifier: License :: OSI Approved :: MIT License
Classifier: Operating System :: OS Independent
Requires-Python: >=3.7
License-File: LICENSE
Requires-Dist: textual
